README.md
setup.py
models/__init__.py
models/bases.py
models/common.py
models/config.py
models/engine.py
models/experimental.py
models/hubconf.py
models/yolo.py
models/http/__init__.py
models/http/event_handlers.py
models/http/server.py
models/http/routes/__init__.py
models/http/routes/detector.py
models/http/routes/heartbeat.py
models/http/routes/router.py
models/http/schemas/__init__.py
models/http/schemas/heartbeat.py
models/http/schemas/payload.py
models/http/schemas/response.py
models/utils/__init__.py
models/utils/augmentations.py
models/utils/autoanchor.py
models/utils/datasets.py
models/utils/downloads.py
models/utils/general.py
models/utils/helpers.py
models/utils/metrics.py
models/utils/plots.py
models/utils/torch_utils.py
soco_yolo/__init__.py
soco_yolo/bases.py
soco_yolo/common.py
soco_yolo/config.py
soco_yolo/engine.py
soco_yolo/experimental.py
soco_yolo/hubconf.py
soco_yolo/yolo.py
soco_yolo.egg-info/PKG-INFO
soco_yolo.egg-info/SOURCES.txt
soco_yolo.egg-info/dependency_links.txt
soco_yolo.egg-info/requires.txt
soco_yolo.egg-info/top_level.txt
soco_yolo/http/__init__.py
soco_yolo/http/event_handlers.py
soco_yolo/http/server.py
soco_yolo/http/routes/__init__.py
soco_yolo/http/routes/detector.py
soco_yolo/http/routes/heartbeat.py
soco_yolo/http/routes/router.py
soco_yolo/http/schemas/__init__.py
soco_yolo/http/schemas/heartbeat.py
soco_yolo/http/schemas/payload.py
soco_yolo/http/schemas/response.py
soco_yolo/utils/__init__.py
soco_yolo/utils/augmentations.py
soco_yolo/utils/autoanchor.py
soco_yolo/utils/datasets.py
soco_yolo/utils/downloads.py
soco_yolo/utils/general.py
soco_yolo/utils/helpers.py
soco_yolo/utils/metrics.py
soco_yolo/utils/plots.py
soco_yolo/utils/torch_utils.py
tests/__init__.py
tests/test_engine.py